saltworks/__about__.py
saltworks/__init__.py
saltworks/dataproxy.py
saltworks/fitparameters.py
saltworks/indextools.py
saltworks/linearmodels.py
saltworks/plottools.py
saltworks/robuststat.py
saltworks/selinv.py
saltworks-0.0.1.dist-info/METADATA
saltworks-0.0.1.dist-info/WHEEL
saltworks-0.0.1.dist-info/licenses/LICENSE.txt
saltworks-0.0.1.dist-info/RECORD
