Metadata-Version: 2.1
Name: saltworks
Version: 0.0.1
Project-URL: Documentation, https://gitlab.in2p3.fr/lemaitre/saltworks#readme
Project-URL: Issues, https://gitlab.in2p3.fr/lemaitre/saltworks/issues
Project-URL: Source, https://gitlab.in2p3.fr/lemaitre/saltworks
Author-email: Leander Lacroix <leander.lacroix.dev@protonmail.com>
License-Expression: MIT
License-File: LICENSE.txt
Classifier: Development Status :: 4 - Beta
Classifier: Programming Language :: Python
Classifier: Programming Language :: Python :: 3.8
Classifier: Programming Language :: Python :: 3.9
Classifier: Programming Language :: Python :: 3.10
Classifier: Programming Language :: Python :: 3.11
Classifier: Programming Language :: Python :: 3.12
Classifier: Programming Language :: Python :: Implementation :: CPython
Classifier: Programming Language :: Python :: Implementation :: PyPy
Requires-Python: >=3.8
